{"startBiome":13,"avableToRandom": [1,3,7],"segmentCounts":8,"biomes": [{"biomeType":1,"setNextSegmentDistance":100,"segmentSaveDublicateIndexes":2,"biomeSaveDublicateIndexes":2,"minBiomeSegments":10,"maxBiomeSegments":20,"biomeSpawnChange":0.5,"nextBiome":0,"segments": [{"spawnConfig": [{"indexses": [-1,-1,-1,-1,-1]},{"indexses": [0,1,1,1,6]},{"indexses": [1,7,2,1,1]},{"indexses": [-1,-1,-1,-1,-1]},{"indexses": [0,2,0,0,0]},{"indexses": [-1,-1,3,-1,-1]},{"indexses": [1,1,1,1,7]},{"indexses": [1,1,1,6,7]},{"indexses": [-1,-1,-1,-1,-1]}],"parameters": [{"indexses": [0,0,0,0,0]},{"indexses": [1,0,0,0,0]},{"indexses": [8,2,3,4,5]},{"indexses": [0,0,0,0,0]},{"indexses": [0,0,0,0,0]},{"indexses": [0,0,0,0,0]},{"indexses": [8,0,2,0,1]},{"indexses": [1,0,0,0,0]},{"indexses": [0,0,0,0,0]}]},{"spawnConfig": [{"indexses": [-1,-1,-1,-1,-1]},{"indexses": [1,0,4,0,0]},{"indexses": [1,1,2,7,4]},{"indexses": [-1,-1,-1,8,-1]},{"indexses": [0,4,5,0,13]},{"indexses": [-1,-1,-1,-1,-1]},{"indexses": [1,1,1,1,4]},{"indexses": [1,0,4,0,0]},{"indexses": [-1,-1,-1,-1,-1]}],"parameters": [{"indexses": [0,0,0,0,0]},{"indexses": [1,0,0,0,0]},{"indexses": [8,6,1,3,7]},{"indexses": [0,0,0,-1,0]},{"indexses": [0,0,0,0,0]},{"indexses": [0,0,0,0,0]},{"indexses": [8,7,5,4,6]},{"indexses": [1,0,0,0,0]},{"indexses": [0,0,0,0,0]}]},{"spawnConfig": [{"indexses": [-1,-1,-1,-1,-1]},{"indexses": [8,0,4,0,0]},{"indexses": [1,1,2,1,4]},{"indexses": [-1,-1,8,-1,-1]},{"indexses": [0,12,6,0,0]},{"indexses": [-1,-1,-1,-1,-1]},{"indexses": [1,7,1,1,4]},{"indexses": [1,0,4,0,6]},{"indexses": [-1,-1,-1,-1,-1]}],"parameters": [{"indexses": [0,0,0,0,0]},{"indexses": [1,0,0,0,0]},{"indexses": [8,5,0,6,0]},{"indexses": [0,0,-1,0,0]},{"indexses": [0,0,0,0,0]},{"indexses": [0,0,0,0,0]},{"indexses": [8,2,6,0,0]},{"indexses": [1,0,0,0,0]},{"indexses": [0,0,0,0,0]}]},{"spawnConfig": [{"indexses": [-1,-1,-1,-1,-1]},{"indexses": [1,0,4,0,0]},{"indexses": [1,1,2,1,4]},{"indexses": [-1,-1,8,-1,-1]},{"indexses": [0,0,5,0,0]},{"indexses": [-1,-1,-1,8,-1]},{"indexses": [7,1,1,1,4]},{"indexses": [1,0,4,0,0]},{"indexses": [-1,-1,-1,-1,-1]}],"parameters": [{"indexses": [0,0,0,0,0]},{"indexses": [0,0,0,0,0]},{"indexses": [8,0,4,0,6]},{"indexses": [0,0,-1,0,0]},{"indexses": [0,0,0,0,0]},{"indexses": [0,0,0,0,0]},{"indexses": [4,6,5,7,0]},{"indexses": [0,0,0,0,0]},{"indexses": [0,0,0,0,0]}]},{"spawnConfig": [{"indexses": [-1,-1,-1,-1,-1]},{"indexses": [1,0,4,0,0]},{"indexses": [1,1,2,1,4]},{"indexses": [-1,8,-1,-1,-1]},{"indexses": [0,0,6,0,0]},{"indexses": [-1,-1,14,-1,8]},{"indexses": [1,1,1,1,4]},{"indexses": [1,0,4,0,0]},{"indexses": [-1,-1,-1,-1,-1]}],"parameters": [{"indexses": [0,0,0,0,0]},{"indexses": [0,0,0,0,0]},{"indexses": [8,4,5,0,6]},{"indexses": [0,-1,0,0,0]},{"indexses": [0,0,0,0,0]},{"indexses": [0,0,0,0,0]},{"indexses": [8,7,6,6,0]},{"indexses": [0,0,0,0,0]},{"indexses": [0,0,0,0,0]}]},{"spawnConfig": [{"indexses": [-1,-1,-1,-1,-1]},{"indexses": [1,0,4,0,0]},{"indexses": [1,7,2,1,4]},{"indexses": [-1,-1,8,-1,-1]},{"indexses": [0,4,5,0,0]},{"indexses": [-1,-1,-1,-1,3]},{"indexses": [1,1,1,1,4]},{"indexses": [1,0,4,0,0]},{"indexses": [-1,-1,-1,-1,-1]}],"parameters": [{"indexses": [0,0,0,0,0]},{"indexses": [0,0,0,0,0]},{"indexses": [8,3,0,6,0]},{"indexses": [0,0,-1,0,0]},{"indexses": [0,0,0,0,0]},{"indexses": [0,0,0,0,0]},{"indexses": [8,6,7,4,0]},{"indexses": [0,0,0,0,0]},{"indexses": [0,0,0,0,0]}]}],"transitions": [{"previousBiome":3,"useTransition":true,"copyFromIndex":-1,"segment":{"spawnConfig": [{"indexses": [-1,-1,-1,-1,-1]},{"indexses": [0,1,0,1,1]},{"indexses": [9,8,11,2,2]},{"indexses": [-1,-1,-1,-1,-1]},{"indexses": [0,0,12,0,0]},{"indexses": [-1,-1,-1,-1,-1]},{"indexses": [9,9,11,3,2]},{"indexses": [0,0,0,0,0]},{"indexses": [-1,-1,-1,-1,-1]}],"parameters": [{"indexses": [0,0,0,0,0]},{"indexses": [5,0,0,0,0]},{"indexses": [0,4,-1,4,7]},{"indexses": [0,0,0,-1,0]},{"indexses": [0,0,0,0,0]},{"indexses": [0,0,0,0,0]},{"indexses": [4,7,-1,7,0]},{"indexses": [0,5,0,5,0]},{"indexses": [0,0,0,0,0]}]}},{"previousBiome":7,"useTransition":true,"copyFromIndex":0,"segment":{"spawnConfig": [{"indexses": []},{"indexses": []},{"indexses": []},{"indexses": []},{"indexses": []},{"indexses": []},{"indexses": []},{"indexses": []},{"indexses": []}],"parameters": [{"indexses": []},{"indexses": []},{"indexses": []},{"indexses": []},{"indexses": []},{"indexses": []},{"indexses": []},{"indexses": []},{"indexses": []}]}},{"previousBiome":4,"useTransition":true,"copyFromIndex":0,"segment":{"spawnConfig": [{"indexses": []},{"indexses": []},{"indexses": []},{"indexses": []},{"indexses": []},{"indexses": []},{"indexses": []},{"indexses": []},{"indexses": []}],"parameters": [{"indexses": []},{"indexses": []},{"indexses": []},{"indexses": []},{"indexses": []},{"indexses": []},{"indexses": []},{"indexses": []},{"indexses": []}]}},{"previousBiome":4,"useTransition":false,"copyFromIndex":2,"segment":{"spawnConfig": [{"indexses": []},{"indexses": []},{"indexses": []},{"indexses": []},{"indexses": []},{"indexses": []},{"indexses": []},{"indexses": []},{"indexses": []}],"parameters": [{"indexses": []},{"indexses": []},{"indexses": []},{"indexses": []},{"indexses": []},{"indexses": []},{"indexses": []},{"indexses": []},{"indexses": []}]}},{"previousBiome":5,"useTransition":false,"copyFromIndex":-1,"segment":{"spawnConfig": [{"indexses": []},{"indexses": []},{"indexses": []},{"indexses": []},{"indexses": []},{"indexses": []},{"indexses": []},{"indexses": []},{"indexses": []}],"parameters": [{"indexses": []},{"indexses": []},{"indexses": []},{"indexses": []},{"indexses": []},{"indexses": []},{"indexses": []},{"indexses": []},{"indexses": []}]}},{"previousBiome":6,"useTransition":false,"copyFromIndex":4,"segment":{"spawnConfig": [{"indexses": []},{"indexses": []},{"indexses": []},{"indexses": []},{"indexses": []},{"indexses": []},{"indexses": []},{"indexses": []},{"indexses": []}],"parameters": [{"indexses": []},{"indexses": []},{"indexses": []},{"indexses": []},{"indexses": []},{"indexses": []},{"indexses": []},{"indexses": []},{"indexses": []}]}}]},{"biomeType":3,"setNextSegmentDistance":100,"segmentSaveDublicateIndexes":2,"biomeSaveDublicateIndexes":2,"minBiomeSegments":10,"maxBiomeSegments":20,"biomeSpawnChange":0.5,"nextBiome":0,"segments": [{"spawnConfig": [{"indexses": [-1,-1,-1,-1,-1,-1]},{"indexses": [0,11,-1,10,-1,1]},{"indexses": [9,8,-1,10,-1,9]},{"indexses": [-1,-1,-1,-1,-1,-1]},{"indexses": [0,0,0,0,0,0]},{"indexses": [-1,-1,-1,-1,-1,-1]},{"indexses": [8,8,9,9,8,9]},{"indexses": [0,11,0,0,11,0]},{"indexses": [-1,-1,-1,-1,-1,-1]}],"parameters": [{"indexses": [0,0,0,0,0,0]},{"indexses": [0,0,0,0,0,0]},{"indexses": [0,0,0,4,0,0]},{"indexses": [0,0,0,0,0,0]},{"indexses": [0,0,0,0,0,0]},{"indexses": [0,0,0,0,0,0]},{"indexses": [0,0,0,0,0,0]},{"indexses": [0,0,0,0,0,0]},{"indexses": [0,0,0,0,0,0]}]},{"spawnConfig": [{"indexses": [-1,-1,-1,-1,-1,-1]},{"indexses": [0,11,0,0,11,0]},{"indexses": [8,9,9,8,8,9]},{"indexses": [-1,-1,-1,-1,8,-1]},{"indexses": [0,0,0,0,0,0]},{"indexses": [-1,-1,8,-1,-1,-1]},{"indexses": [9,8,-1,10,-1,9]},{"indexses": [0,11,-1,10,-1,0]},{"indexses": [-1,-1,-1,-1,-1,-1]}],"parameters": [{"indexses": [0,0,0,0,0,0]},{"indexses": [0,0,0,0,0,0]},{"indexses": [0,0,0,0,0,0]},{"indexses": [0,0,0,0,-1,0]},{"indexses": [0,0,0,0,0,0]},{"indexses": [0,0,0,0,0,0]},{"indexses": [0,0,0,3,0,0]},{"indexses": [0,-1,0,0,0,10]},{"indexses": [0,0,0,0,0,0]}]},{"spawnConfig": [{"indexses": [-1,-1,-1,-1,-1,-1]},{"indexses": [0,12,0,0,11,0]},{"indexses": [9,8,8,9,8,9]},{"indexses": [-1,-1,-1,-1,-1,-1]},{"indexses": [0,0,2,0,0,0]},{"indexses": [-1,-1,8,-1,-1,-1]},{"indexses": [9,9,-1,10,-1,8]},{"indexses": [0,11,-1,10,-1,0]},{"indexses": [-1,-1,-1,-1,-1,-1]}],"parameters": [{"indexses": [0,0,0,0,0,0]},{"indexses": [0,0,0,0,0,0]},{"indexses": [0,0,0,0,0,0]},{"indexses": [0,0,0,0,0,0]},{"indexses": [0,0,0,0,0,0]},{"indexses": [0,0,0,0,0,0]},{"indexses": [0,0,0,4,5,5]},{"indexses": [0,-1,0,0,9,10]},{"indexses": [0,0,0,0,0,0]}]},{"spawnConfig": [{"indexses": [-1,-1,-1,-1,-1,-1]},{"indexses": [0,11,0,0,12,0]},{"indexses": [9,8,8,9,8,9]},{"indexses": [-1,-1,-1,-1,8,-1]},{"indexses": [0,0,0,4,0,0]},{"indexses": [8,-1,-1,-1,-1,-1]},{"indexses": [9,9,8,8,9,8]},{"indexses": [0,11,0,0,11,0]},{"indexses": [-1,-1,-1,-1,-1,-1]}],"parameters": [{"indexses": [0,0,0,0,0,0]},{"indexses": [0,0,0,0,0,9]},{"indexses": [0,0,10,10,0,10]},{"indexses": [-1,0,0,0,-1,0]},{"indexses": [0,0,0,0,0,0]},{"indexses": [0,0,0,0,0,0]},{"indexses": [10,0,10,10,0,0]},{"indexses": [0,0,0,0,0,0]},{"indexses": [0,0,0,0,0,0]}]},{"spawnConfig": [{"indexses": [-1,-1,-1,-1,-1,-1]},{"indexses": [-1,10,-1,0,13,0]},{"indexses": [-1,10,-1,9,8,9]},{"indexses": [-1,-1,-1,-1,8,-1]},{"indexses": [2,0,0,4,0,0]},{"indexses": [-1,-1,-1,8,-1,-1]},{"indexses": [9,9,8,8,9,8]},{"indexses": [0,11,0,0,11,0]},{"indexses": [-1,-1,-1,-1,-1,-1]}],"parameters": [{"indexses": [0,0,0,0,0,0]},{"indexses": [10,0,0,0,0,9]},{"indexses": [4,6,0,10,0,10]},{"indexses": [-1,0,0,0,-1,0]},{"indexses": [0,0,0,0,0,0]},{"indexses": [0,0,0,0,0,0]},{"indexses": [10,0,10,10,0,0]},{"indexses": [0,0,0,0,0,0]},{"indexses": [0,0,0,0,0,0]}]},{"spawnConfig": [{"indexses": [-1,-1,-1,-1,-1,-1]},{"indexses": [-1,10,-1,0,12,0]},{"indexses": [-1,10,-1,9,8,9]},{"indexses": [9,-1,-1,-1,-1,-1]},{"indexses": [2,0,0,4,0,0]},{"indexses": [-1,-1,-1,8,-1,-1]},{"indexses": [-1,10,-1,8,9,8]},{"indexses": [-1,10,-1,0,13,0]},{"indexses": [-1,-1,-1,-1,-1,-1]}],"parameters": [{"indexses": [0,0,0,0,0,0]},{"indexses": [10,0,0,0,0,9]},{"indexses": [4,6,0,10,0,10]},{"indexses": [-1,0,0,0,-1,0]},{"indexses": [0,0,0,0,0,0]},{"indexses": [0,0,0,0,0,0]},{"indexses": [5,3,0,10,0,0]},{"indexses": [10,0,9,0,0,0]},{"indexses": [0,0,0,0,0,0]}]}],"transitions": [{"previousBiome":1,"useTransition":true,"copyFromIndex":-1,"segment":{"spawnConfig": [{"indexses": [-1,-1,-1,-1,-1]},{"indexses": [7,1,0,11,0]},{"indexses": [2,3,11,8,8]},{"indexses": [-1,-1,-1,-1,-1]},{"indexses": [0,0,12,0,0]},{"indexses": [-1,-1,-1,-1,-1]},{"indexses": [1,2,11,8,9]},{"indexses": [6,8,0,11,0]},{"indexses": [-1,-1,-1,-1,-1]}],"parameters": [{"indexses": [0,0,0,0,0]},{"indexses": [2,0,3,0,0]},{"indexses": [0,2,0,0,0]},{"indexses": [0,0,0,0,0]},{"indexses": [0,0,0,0,0]},{"indexses": [0,0,0,0,0]},{"indexses": [2,3,0,0,0]},{"indexses": [2,0,3,0,0]},{"indexses": [0,0,0,0,0]}]}},{"previousBiome":2,"useTransition":true,"copyFromIndex":0,"segment":{"spawnConfig": [{"indexses": []},{"indexses": []},{"indexses": []},{"indexses": []},{"indexses": []},{"indexses": []},{"indexses": []},{"indexses": []},{"indexses": []}],"parameters": [{"indexses": []},{"indexses": []},{"indexses": []},{"indexses": []},{"indexses": []},{"indexses": []},{"indexses": []},{"indexses": []},{"indexses": []}]}},{"previousBiome":5,"useTransition":true,"copyFromIndex":0,"segment":{"spawnConfig": [{"indexses": []},{"indexses": []},{"indexses": []},{"indexses": []},{"indexses": []},{"indexses": []},{"indexses": []},{"indexses": []},{"indexses": []}],"parameters": [{"indexses": []},{"indexses": []},{"indexses": []},{"indexses": []},{"indexses": []},{"indexses": []},{"indexses": []},{"indexses": []},{"indexses": []}]}},{"previousBiome":7,"useTransition":false,"copyFromIndex":-1,"segment":{"spawnConfig": [{"indexses": []},{"indexses": []},{"indexses": []},{"indexses": []},{"indexses": []},{"indexses": []},{"indexses": []},{"indexses": []},{"indexses": []}],"parameters": [{"indexses": []},{"indexses": []},{"indexses": []},{"indexses": []},{"indexses": []},{"indexses": []},{"indexses": []},{"indexses": []},{"indexses": []}]}},{"previousBiome":0,"useTransition":false,"copyFromIndex":-1,"segment":{"spawnConfig": [{"indexses": []},{"indexses": []},{"indexses": []},{"indexses": []},{"indexses": []},{"indexses": []},{"indexses": []},{"indexses": []},{"indexses": []}],"parameters": [{"indexses": []},{"indexses": []},{"indexses": []},{"indexses": []},{"indexses": []},{"indexses": []},{"indexses": []},{"indexses": []},{"indexses": []}]}},{"previousBiome":0,"useTransition":false,"copyFromIndex":-1,"segment":{"spawnConfig": [{"indexses": []},{"indexses": []},{"indexses": []},{"indexses": []},{"indexses": []},{"indexses": []},{"indexses": []},{"indexses": []},{"indexses": []}],"parameters": [{"indexses": []},{"indexses": []},{"indexses": []},{"indexses": []},{"indexses": []},{"indexses": []},{"indexses": []},{"indexses": []},{"indexses": []}]}}]},{"biomeType":7,"setNextSegmentDistance":100,"segmentSaveDublicateIndexes":2,"biomeSaveDublicateIndexes":2,"minBiomeSegments":10,"maxBiomeSegments":20,"biomeSpawnChange":0.5,"nextBiome":0,"segments": [{"spawnConfig": [{"indexses": [-1,-1,-1,-1,-1,-1]},{"indexses": [0,0,0,0,0,0]},{"indexses": [8,8,9,9,9,8]},{"indexses": [-1,-1,-1,-1,8,-1]},{"indexses": [0,0,0,0,14,0]},{"indexses": [-1,-1,14,-1,-1,-1]},{"indexses": [9,8,8,8,9,8]},{"indexses": [0,0,14,0,0,0]},{"indexses": [-1,-1,-1,-1,-1,-1]}],"parameters": [{"indexses": [0,0,0,0,0,0]},{"indexses": [12,7,11,0,7,11]},{"indexses": [10,0,10,10,0,10]},{"indexses": [0,0,0,0,-1,0]},{"indexses": [0,0,0,0,0,0]},{"indexses": [0,0,0,0,0,0]},{"indexses": [10,0,0,10,10,10]},{"indexses": [14,0,0,0,6,11]},{"indexses": [0,0,0,0,0,0]}]},{"spawnConfig": [{"indexses": [-1,-1,-1,-1,-1,-1]},{"indexses": [-1,10,-1,0,0,0]},{"indexses": [-1,10,-1,9,9,8]},{"indexses": [-1,-1,-1,-1,-1,8]},{"indexses": [2,0,0,12,0,2]},{"indexses": [8,-1,-1,-1,-1,-1]},{"indexses": [9,8,8,8,9,8]},{"indexses": [0,0,14,0,0,0]},{"indexses": [-1,-1,-1,-1,-1,-1]}],"parameters": [{"indexses": [0,0,0,0,0,0]},{"indexses": [12,0,11,0,7,11]},{"indexses": [0,6,0,10,0,10]},{"indexses": [0,0,0,0,0,-1]},{"indexses": [0,0,0,0,0,0]},{"indexses": [0,0,0,0,0,0]},{"indexses": [10,0,0,10,10,10]},{"indexses": [14,0,0,0,6,11]},{"indexses": [0,0,0,0,0,0]}]},{"spawnConfig": [{"indexses": [-1,-1,-1,-1,-1,-1]},{"indexses": [0,15,0,0,0,0]},{"indexses": [9,8,8,9,9,8]},{"indexses": [8,-1,-1,-1,-1,-1]},{"indexses": [0,2,0,0,0,2]},{"indexses": [3,-1,-1,8,-1,-1]},{"indexses": [9,8,-1,10,-1,8]},{"indexses": [0,16,-1,10,-1,0]},{"indexses": [-1,-1,-1,-1,-1,-1]}],"parameters": [{"indexses": [0,0,0,0,0,0]},{"indexses": [12,0,11,0,7,11]},{"indexses": [10,10,0,10,0,10]},{"indexses": [-1,0,0,0,0,0]},{"indexses": [0,0,0,0,0,0]},{"indexses": [0,0,0,0,0,0]},{"indexses": [10,0,0,4,10,10]},{"indexses": [13,0,0,0,6,11]},{"indexses": [0,0,0,0,0,0]}]},{"spawnConfig": [{"indexses": [-1,-1,-1,-1,-1,-1]},{"indexses": [-1,10,-1,0,14,0]},{"indexses": [-1,10,-1,8,9,8]},{"indexses": [-1,-1,-1,8,-1,-1]},{"indexses": [0,2,0,0,0,0]},{"indexses": [-1,-1,-1,3,-1,-1]},{"indexses": [9,8,9,-1,10,-1]},{"indexses": [0,0,0,-1,10,-1]},{"indexses": [-1,-1,-1,-1,-1,-1]}],"parameters": [{"indexses": [0,0,0,0,0,0]},{"indexses": [4,0,0,0,0,0]},{"indexses": [4,5,4,6,0,10]},{"indexses": [0,0,0,-1,0,0]},{"indexses": [0,0,0,0,0,0]},{"indexses": [0,0,0,0,0,0]},{"indexses": [10,10,10,0,4,4]},{"indexses": [12,7,11,0,0,6]},{"indexses": [0,0,0,0,0,0]}]},{"spawnConfig": [{"indexses": [-1,-1,-1,-1,-1,-1]},{"indexses": [0,0,0,0,0,0]},{"indexses": [9,8,9,8,9,8]},{"indexses": [-1,-1,-1,8,-1,-1]},{"indexses": [0,2,0,0,0,0]},{"indexses": [-1,-1,-1,3,-1,-1]},{"indexses": [9,8,9,8,8,9]},{"indexses": [0,0,0,0,0,0]},{"indexses": [-1,-1,-1,-1,-1,-1]}],"parameters": [{"indexses": [0,0,0,0,0,0]},{"indexses": [12,7,11,0,7,11]},{"indexses": [0,0,0,0,0,0]},{"indexses": [0,0,0,-1,0,0]},{"indexses": [0,0,0,0,0,0]},{"indexses": [0,0,0,0,0,0]},{"indexses": [0,0,0,0,0,0]},{"indexses": [12,7,11,0,7,11]},{"indexses": [0,0,0,0,0,0]}]},{"spawnConfig": [{"indexses": [-1,-1,-1,-1,-1,-1]},{"indexses": [0,0,0,0,0,0]},{"indexses": [9,8,9,8,9,8]},{"indexses": [-1,-1,-1,8,-1,-1]},{"indexses": [0,2,0,0,2,0]},{"indexses": [-1,-1,8,-1,-1,-1]},{"indexses": [9,8,9,8,8,9]},{"indexses": [0,0,0,0,0,0]},{"indexses": [-1,-1,-1,-1,-1,-1]}],"parameters": [{"indexses": [0,0,0,0,0,0]},{"indexses": [12,7,11,0,7,11]},{"indexses": [0,0,0,0,0,0]},{"indexses": [0,0,0,-1,0,0]},{"indexses": [0,0,0,0,0,0]},{"indexses": [0,0,0,0,0,0]},{"indexses": [0,0,0,0,0,0]},{"indexses": [12,7,11,0,7,11]},{"indexses": [0,0,0,0,0,0]}]}],"transitions": [{"previousBiome":1,"useTransition":true,"copyFromIndex":-1,"segment":{"spawnConfig": [{"indexses": [-1,-1,-1,-1,-1]},{"indexses": [0,1,0,1,1]},{"indexses": [2,3,11,8,9]},{"indexses": [-1,-1,-1,-1,-1]},{"indexses": [0,0,12,0,0]},{"indexses": [-1,-1,-1,-1,-1]},{"indexses": [2,2,11,8,8]},{"indexses": [0,0,0,0,0]},{"indexses": [-1,-1,-1,-1,-1]}],"parameters": [{"indexses": [0,0,0,0,0]},{"indexses": [5,0,0,0,0]},{"indexses": [3,4,0,4,7]},{"indexses": [0,0,0,-1,0]},{"indexses": [0,0,0,0,0]},{"indexses": [0,0,0,0,0]},{"indexses": [4,7,0,7,0]},{"indexses": [0,5,0,5,0]},{"indexses": [0,0,0,0,0]}]}},{"previousBiome":2,"useTransition":true,"copyFromIndex":0,"segment":{"spawnConfig": [{"indexses": []},{"indexses": []},{"indexses": []},{"indexses": []},{"indexses": []},{"indexses": []},{"indexses": []},{"indexses": []},{"indexses": []}],"parameters": [{"indexses": []},{"indexses": []},{"indexses": []},{"indexses": []},{"indexses": []},{"indexses": []},{"indexses": []},{"indexses": []},{"indexses": []}]}},{"previousBiome":5,"useTransition":true,"copyFromIndex":0,"segment":{"spawnConfig": [{"indexses": []},{"indexses": []},{"indexses": []},{"indexses": []},{"indexses": []},{"indexses": []},{"indexses": []},{"indexses": []},{"indexses": []}],"parameters": [{"indexses": []},{"indexses": []},{"indexses": []},{"indexses": []},{"indexses": []},{"indexses": []},{"indexses": []},{"indexses": []},{"indexses": []}]}},{"previousBiome":3,"useTransition":false,"copyFromIndex":-1,"segment":{"spawnConfig": [{"indexses": []},{"indexses": []},{"indexses": []},{"indexses": []},{"indexses": []},{"indexses": []},{"indexses": []},{"indexses": []},{"indexses": []}],"parameters": [{"indexses": []},{"indexses": []},{"indexses": []},{"indexses": []},{"indexses": []},{"indexses": []},{"indexses": []},{"indexses": []},{"indexses": []}]}},{"previousBiome":0,"useTransition":false,"copyFromIndex":-1,"segment":{"spawnConfig": [{"indexses": []},{"indexses": []},{"indexses": []},{"indexses": []},{"indexses": []},{"indexses": []},{"indexses": []},{"indexses": []},{"indexses": []}],"parameters": [{"indexses": []},{"indexses": []},{"indexses": []},{"indexses": []},{"indexses": []},{"indexses": []},{"indexses": []},{"indexses": []},{"indexses": []}]}},{"previousBiome":0,"useTransition":false,"copyFromIndex":-1,"segment":{"spawnConfig": [{"indexses": []},{"indexses": []},{"indexses": []},{"indexses": []},{"indexses": []},{"indexses": []},{"indexses": []},{"indexses": []},{"indexses": []}],"parameters": [{"indexses": []},{"indexses": []},{"indexses": []},{"indexses": []},{"indexses": []},{"indexses": []},{"indexses": []},{"indexses": []},{"indexses": []}]}}]},{"biomeType":13,"setNextSegmentDistance":100,"segmentSaveDublicateIndexes":2,"biomeSaveDublicateIndexes":2,"minBiomeSegments":2,"maxBiomeSegments":4,"biomeSpawnChange":0,"nextBiome":1,"segments": [{"spawnConfig": [{"indexses": [-1,-1,-1,-1,-1]},{"indexses": [0,1,1,1,6]},{"indexses": [1,7,2,1,1]},{"indexses": [-1,-1,-1,3,-1]},{"indexses": [0,0,0,0,0]},{"indexses": [-1,-1,-1,-1,-1]},{"indexses": [1,1,1,1,7]},{"indexses": [1,1,1,6,7]},{"indexses": [-1,-1,-1,-1,-1]}],"parameters": [{"indexses": [0,0,0,0,0]},{"indexses": [1,0,0,0,0]},{"indexses": [8,2,3,0,5]},{"indexses": [0,0,0,0,0]},{"indexses": [0,0,0,0,0]},{"indexses": [0,0,0,0,0]},{"indexses": [8,0,2,0,1]},{"indexses": [1,0,0,0,0]},{"indexses": [0,0,0,0,0]}]},{"spawnConfig": [{"indexses": [-1,-1,-1,-1,-1]},{"indexses": [1,0,4,0,0]},{"indexses": [1,1,2,7,4]},{"indexses": [-1,-1,-1,-1,-1]},{"indexses": [0,0,0,0,0]},{"indexses": [-1,-1,-1,-1,-1]},{"indexses": [1,1,1,1,4]},{"indexses": [1,0,4,0,0]},{"indexses": [-1,-1,-1,-1,-1]}],"parameters": [{"indexses": [0,0,0,0,0]},{"indexses": [1,0,0,0,0]},{"indexses": [8,6,1,3,0]},{"indexses": [0,0,0,0,0]},{"indexses": [0,0,0,0,0]},{"indexses": [0,0,0,0,0]},{"indexses": [8,0,5,0,0]},{"indexses": [1,0,0,0,0]},{"indexses": [0,0,0,0,0]}]},{"spawnConfig": [{"indexses": [-1,-1,-1,-1,-1]},{"indexses": [8,0,4,0,0]},{"indexses": [1,1,2,1,4]},{"indexses": [8,-1,-1,-1,-1]},{"indexses": [0,0,0,0,0]},{"indexses": [-1,-1,-1,-1,-1]},{"indexses": [1,7,1,1,4]},{"indexses": [1,0,4,0,6]},{"indexses": [-1,-1,-1,-1,-1]}],"parameters": [{"indexses": [0,0,0,0,0]},{"indexses": [1,0,0,0,0]},{"indexses": [8,5,0,6,0]},{"indexses": [-1,0,0,0,0]},{"indexses": [0,0,0,0,0]},{"indexses": [0,0,0,0,0]},{"indexses": [8,2,6,0,0]},{"indexses": [1,0,0,0,0]},{"indexses": [0,0,0,0,0]}]},{"spawnConfig": [{"indexses": [-1,-1,-1,-1,-1]},{"indexses": [1,0,4,0,0]},{"indexses": [1,1,2,1,4]},{"indexses": [-1,-1,-1,-1,-1]},{"indexses": [0,0,0,0,0]},{"indexses": [-1,8,-1,-1,-1]},{"indexses": [7,1,1,1,4]},{"indexses": [1,0,4,0,0]},{"indexses": [-1,-1,-1,-1,-1]}],"parameters": [{"indexses": [0,0,0,0,0]},{"indexses": [0,0,0,0,0]},{"indexses": [8,0,4,0,0]},{"indexses": [0,0,0,0,0]},{"indexses": [0,0,0,0,0]},{"indexses": [0,0,0,0,0]},{"indexses": [4,6,5,0,0]},{"indexses": [0,0,0,0,0]},{"indexses": [0,0,0,0,0]}]},{"spawnConfig": [{"indexses": [-1,-1,-1,-1,-1]},{"indexses": [1,0,4,0,0]},{"indexses": [1,1,2,1,4]},{"indexses": [3,-1,-1,-1,-1]},{"indexses": [0,0,0,0,0]},{"indexses": [-1,-1,-1,-1,8]},{"indexses": [1,1,1,1,4]},{"indexses": [1,0,4,0,0]},{"indexses": [-1,-1,-1,-1,-1]}],"parameters": [{"indexses": [0,0,0,0,0]},{"indexses": [0,0,0,0,0]},{"indexses": [8,4,5,0,0]},{"indexses": [0,0,0,0,0]},{"indexses": [0,0,0,0,0]},{"indexses": [0,0,0,0,0]},{"indexses": [8,0,0,0,0]},{"indexses": [0,0,0,0,0]},{"indexses": [0,0,0,0,0]}]},{"spawnConfig": [{"indexses": [-1,-1,-1,-1,-1]},{"indexses": [1,0,4,0,0]},{"indexses": [1,7,2,1,4]},{"indexses": [-1,-1,4,-1,-1]},{"indexses": [0,0,0,0,0]},{"indexses": [-1,-1,-1,-1,8]},{"indexses": [1,1,1,1,4]},{"indexses": [1,0,4,0,0]},{"indexses": [-1,-1,-1,-1,-1]}],"parameters": [{"indexses": [0,0,0,0,0]},{"indexses": [0,0,0,0,0]},{"indexses": [8,3,0,0,0]},{"indexses": [0,0,0,0,0]},{"indexses": [0,0,0,0,0]},{"indexses": [0,0,0,0,0]},{"indexses": [8,0,0,4,0]},{"indexses": [0,0,0,0,0]},{"indexses": [0,0,0,0,0]}]}],"transitions": [{"previousBiome":1,"useTransition":false,"copyFromIndex":-1,"segment":{"spawnConfig": [{"indexses": []},{"indexses": []},{"indexses": []},{"indexses": []},{"indexses": []},{"indexses": []},{"indexses": []},{"indexses": []},{"indexses": []}],"parameters": [{"indexses": []},{"indexses": []},{"indexses": []},{"indexses": []},{"indexses": []},{"indexses": []},{"indexses": []},{"indexses": []},{"indexses": []}]}},{"previousBiome":2,"useTransition":false,"copyFromIndex":0,"segment":{"spawnConfig": [{"indexses": []},{"indexses": []},{"indexses": []},{"indexses": []},{"indexses": []},{"indexses": []},{"indexses": []},{"indexses": []},{"indexses": []}],"parameters": [{"indexses": []},{"indexses": []},{"indexses": []},{"indexses": []},{"indexses": []},{"indexses": []},{"indexses": []},{"indexses": []},{"indexses": []}]}},{"previousBiome":3,"useTransition":false,"copyFromIndex":-1,"segment":{"spawnConfig": [{"indexses": []},{"indexses": []},{"indexses": []},{"indexses": []},{"indexses": []},{"indexses": []},{"indexses": []},{"indexses": []},{"indexses": []}],"parameters": [{"indexses": []},{"indexses": []},{"indexses": []},{"indexses": []},{"indexses": []},{"indexses": []},{"indexses": []},{"indexses": []},{"indexses": []}]}},{"previousBiome":4,"useTransition":false,"copyFromIndex":2,"segment":{"spawnConfig": [{"indexses": []},{"indexses": []},{"indexses": []},{"indexses": []},{"indexses": []},{"indexses": []},{"indexses": []},{"indexses": []},{"indexses": []}],"parameters": [{"indexses": []},{"indexses": []},{"indexses": []},{"indexses": []},{"indexses": []},{"indexses": []},{"indexses": []},{"indexses": []},{"indexses": []}]}},{"previousBiome":5,"useTransition":false,"copyFromIndex":-1,"segment":{"spawnConfig": [{"indexses": []},{"indexses": []},{"indexses": []},{"indexses": []},{"indexses": []},{"indexses": []},{"indexses": []},{"indexses": []},{"indexses": []}],"parameters": [{"indexses": []},{"indexses": []},{"indexses": []},{"indexses": []},{"indexses": []},{"indexses": []},{"indexses": []},{"indexses": []},{"indexses": []}]}},{"previousBiome":6,"useTransition":false,"copyFromIndex":4,"segment":{"spawnConfig": [{"indexses": []},{"indexses": []},{"indexses": []},{"indexses": []},{"indexses": []},{"indexses": []},{"indexses": []},{"indexses": []},{"indexses": []}],"parameters": [{"indexses": []},{"indexses": []},{"indexses": []},{"indexses": []},{"indexses": []},{"indexses": []},{"indexses": []},{"indexses": []},{"indexses": []}]}}]},{"biomeType":12,"setNextSegmentDistance":100,"segmentSaveDublicateIndexes":2,"biomeSaveDublicateIndexes":2,"minBiomeSegments":0,"maxBiomeSegments":0,"biomeSpawnChange":0,"nextBiome":0,"segments": [{"spawnConfig": [{"indexses": [5,5,5,5,5]},{"indexses": [0,1,1,1,6]},{"indexses": [1,3,2,1,1]},{"indexses": [-1,-1,-1,9,-1]},{"indexses": [0,0,0,0,0]},{"indexses": [-1,-1,-1,-1,-1]},{"indexses": [1,1,1,1,1]},{"indexses": [1,1,1,6,7]},{"indexses": [5,5,5,5,5]}],"parameters": [{"indexses": [0,5,6,0,0]},{"indexses": [1,0,0,0,0]},{"indexses": [8,0,3,0,5]},{"indexses": [0,0,0,-1,0]},{"indexses": [0,0,0,0,0]},{"indexses": [0,0,0,0,0]},{"indexses": [4,0,2,0,0]},{"indexses": [1,0,0,0,0]},{"indexses": [0,5,6,0,6]}]},{"spawnConfig": [{"indexses": [5,5,5,5,5]},{"indexses": [1,0,4,0,0]},{"indexses": [1,1,2,1,4]},{"indexses": [-1,-1,8,-1,-1]},{"indexses": [0,0,0,0,0]},{"indexses": [8,-1,-1,-1,-1]},{"indexses": [1,1,1,1,4]},{"indexses": [1,0,4,0,0]},{"indexses": [5,5,5,5,5]}],"parameters": [{"indexses": [0,0,0,0,0]},{"indexses": [1,0,0,0,0]},{"indexses": [8,6,1,0,0]},{"indexses": [0,0,-1,0,0]},{"indexses": [0,0,0,0,0]},{"indexses": [0,0,0,0,0]},{"indexses": [8,0,5,1,0]},{"indexses": [1,0,0,0,0]},{"indexses": [0,0,0,0,0]}]},{"spawnConfig": [{"indexses": [5,5,5,5,5]},{"indexses": [8,0,4,0,1]},{"indexses": [1,1,2,1,4]},{"indexses": [-1,-1,-1,-1,9]},{"indexses": [0,0,0,0,0]},{"indexses": [-1,-1,-1,-1,-1]},{"indexses": [1,1,1,1,4]},{"indexses": [1,0,4,0,6]},{"indexses": [5,5,5,5,5]}],"parameters": [{"indexses": [0,0,0,0,0]},{"indexses": [1,0,0,0,0]},{"indexses": [8,5,0,6,0]},{"indexses": [0,0,0,0,-1]},{"indexses": [0,0,0,0,0]},{"indexses": [0,0,0,0,0]},{"indexses": [8,0,6,0,0]},{"indexses": [1,0,0,0,0]},{"indexses": [0,0,0,0,0]}]},{"spawnConfig": [{"indexses": [5,5,5,5,5]},{"indexses": [1,0,4,0,0]},{"indexses": [1,1,2,1,4]},{"indexses": [8,-1,-1,-1,8]},{"indexses": [0,0,0,0,0]},{"indexses": [-1,9,-1,-1,-1]},{"indexses": [1,1,1,1,4]},{"indexses": [1,0,4,0,0]},{"indexses": [5,5,5,5,5]}],"parameters": [{"indexses": [0,0,0,0,0]},{"indexses": [0,0,0,0,0]},{"indexses": [8,0,4,0,0]},{"indexses": [-1,0,0,0,-1]},{"indexses": [0,0,0,0,0]},{"indexses": [0,0,0,0,0]},{"indexses": [8,6,5,0,0]},{"indexses": [0,0,0,0,0]},{"indexses": [0,0,0,0,0]}]},{"spawnConfig": [{"indexses": [5,5,5,5,5]},{"indexses": [1,0,4,0,0]},{"indexses": [1,1,2,1,4]},{"indexses": [8,-1,-1,8,-1]},{"indexses": [0,0,0,0,0]},{"indexses": [-1,8,-1,-1,8]},{"indexses": [1,1,1,1,4]},{"indexses": [1,0,4,0,0]},{"indexses": [5,5,5,5,5]}],"parameters": [{"indexses": [0,0,0,0,0]},{"indexses": [0,0,0,0,0]},{"indexses": [8,4,5,0,0]},{"indexses": [-1,0,0,-1,0]},{"indexses": [0,0,0,0,0]},{"indexses": [0,0,0,0,0]},{"indexses": [8,0,0,0,0]},{"indexses": [0,0,0,0,0]},{"indexses": [0,0,0,0,0]}]},{"spawnConfig": [{"indexses": [5,5,5,5,5]},{"indexses": [1,0,4,0,0]},{"indexses": [1,1,2,1,4]},{"indexses": [8,-1,-1,-1,-1]},{"indexses": [0,0,0,0,0]},{"indexses": [-1,-1,-1,-1,8]},{"indexses": [1,1,1,1,4]},{"indexses": [1,0,4,0,0]},{"indexses": [5,5,5,5,5]}],"parameters": [{"indexses": [0,0,0,0,0]},{"indexses": [0,0,0,0,0]},{"indexses": [8,5,0,0,0]},{"indexses": [-1,0,0,0,0]},{"indexses": [0,0,0,0,0]},{"indexses": [0,0,0,0,0]},{"indexses": [8,0,0,4,0]},{"indexses": [0,0,0,0,0]},{"indexses": [0,0,0,0,0]}]}],"transitions": [{"previousBiome":1,"useTransition":false,"copyFromIndex":-1,"segment":{"spawnConfig": [{"indexses": []},{"indexses": []},{"indexses": []},{"indexses": []},{"indexses": []},{"indexses": []},{"indexses": []},{"indexses": []},{"indexses": []}],"parameters": []}},{"previousBiome":2,"useTransition":false,"copyFromIndex":0,"segment":{"spawnConfig": [{"indexses": []},{"indexses": []},{"indexses": []},{"indexses": []},{"indexses": []},{"indexses": []},{"indexses": []},{"indexses": []},{"indexses": []}],"parameters": []}},{"previousBiome":3,"useTransition":false,"copyFromIndex":-1,"segment":{"spawnConfig": [{"indexses": []},{"indexses": []},{"indexses": []},{"indexses": []},{"indexses": []},{"indexses": []},{"indexses": []},{"indexses": []},{"indexses": []}],"parameters": []}},{"previousBiome":4,"useTransition":false,"copyFromIndex":2,"segment":{"spawnConfig": [{"indexses": []},{"indexses": []},{"indexses": []},{"indexses": []},{"indexses": []},{"indexses": []},{"indexses": []},{"indexses": []},{"indexses": []}],"parameters": []}},{"previousBiome":5,"useTransition":false,"copyFromIndex":-1,"segment":{"spawnConfig": [{"indexses": []},{"indexses": []},{"indexses": []},{"indexses": []},{"indexses": []},{"indexses": []},{"indexses": []},{"indexses": []},{"indexses": []}],"parameters": []}},{"previousBiome":6,"useTransition":false,"copyFromIndex":4,"segment":{"spawnConfig": [{"indexses": []},{"indexses": []},{"indexses": []},{"indexses": []},{"indexses": []},{"indexses": []},{"indexses": []},{"indexses": []},{"indexses": []}],"parameters": []}}]}],"garbageSpawnsConfig":[{"garbageType":0,"spawnChange":0.30000001192092896,"baseReward":1},{"garbageType":1,"spawnChange":0.6000000238418579,"baseReward":1},{"garbageType":2,"spawnChange":0.10000000149011612,"baseReward":10}]}			
			